{"MATLAB": [1, "/categories/matlab/", {"posts": [{"date": "10/04/2016", "isodate": "2016-10-04T10:08:38-05:00", "title": "Programaci\u00f3n en MATLAB, fundamentos y aplicaciones", "url": "/posts/test/"}]}], "blog": [1, "/categories/blog/", {"posts": [{"date": "09/13/2016", "isodate": "2016-09-13T23:27:09-05:00", "title": "Hola mundo", "url": "/posts/hola-mundo/"}]}], "books": [1, "/categories/books/", {"posts": [{"date": "10/04/2016", "isodate": "2016-10-04T10:08:38-05:00", "title": "Programaci\u00f3n en MATLAB, fundamentos y aplicaciones", "url": "/posts/test/"}]}], "otros": [2, "/categories/otros/", {"posts": [{"date": "09/13/2016", "isodate": "2016-09-13T23:42:15-05:00", "title": "Sobre la tesis", "url": "/posts/sobre-la-tesis/"}, {"date": "09/13/2016", "isodate": "2016-09-13T23:27:09-05:00", "title": "Hola mundo", "url": "/posts/hola-mundo/"}]}], "personal": [1, "/categories/personal/", {"posts": [{"date": "09/13/2016", "isodate": "2016-09-13T23:42:15-05:00", "title": "Sobre la tesis", "url": "/posts/sobre-la-tesis/"}]}], "programming": [1, "/categories/programming/", {"posts": [{"date": "10/04/2016", "isodate": "2016-10-04T10:08:38-05:00", "title": "Programaci\u00f3n en MATLAB, fundamentos y aplicaciones", "url": "/posts/test/"}]}]}